python_jr/__init__.py
python_jr/grpc_controller_pb2.py
python_jr/grpc_controller_pb2.pyi
python_jr/grpc_controller_pb2_grpc.py
python_jr/grpc_stdio_pb2.py
python_jr/grpc_stdio_pb2.pyi
python_jr/grpc_stdio_pb2_grpc.py
python_jr/jrplugin.py
python_jr/producer_pb2.py
python_jr/producer_pb2.pyi
python_jr/producer_pb2_grpc.py
python_jr-2.1.3.dist-info/METADATA
python_jr-2.1.3.dist-info/WHEEL
python_jr-2.1.3.dist-info/RECORD
