Metadata-Version: 2.1
Name: python-jr
Version: 2.1.3
Summary: python plugin system for jr, the data random generator
Author: JR Team
Requires-Python: >=3.9,<4.0
Classifier: Programming Language :: Python :: 3
Classifier: Programming Language :: Python :: 3.9
Classifier: Programming Language :: Python :: 3.10
Classifier: Programming Language :: Python :: 3.11
Requires-Dist: grpcio (>=1.67.0,<2.0.0)
Requires-Dist: grpcio-health-checking (>=1.59.0,<2.0.0)
Requires-Dist: grpcio-tools (>=1.66.0,<2.0.0)
Requires-Dist: protobuf (>=5.27.3,<6.0.0)
Requires-Dist: setuptools (>=73.0.1,<74.0.0)
